{
    "update_time_utc": "2025-07-17 19:52:49 UTC",
    "top_up_20": [
        {
            "代码": "PEP",
            "名称": "PepsiCo, Inc.",
            "Percent": 7.5212354759670985
        },
        {
            "代码": "AVGO",
            "名称": "Broadcom Inc.",
            "Percent": 2.0423118546354315
        },
        {
            "代码": "NFLX",
            "名称": "Netflix, Inc.",
            "Percent": 1.8928215071652148
        },
        {
            "代码": "CSCO",
            "名称": "Cisco Systems, Inc.",
            "Percent": 1.5506910790672277
        },
        {
            "代码": "MSFT",
            "名称": "Microsoft Corporation",
            "Percent": 1.315221802595292
        },
        {
            "代码": "NVDA",
            "名称": "NVIDIA Corporation",
            "Percent": 1.2136333816049
        },
        {
            "代码": "NVDA",
            "名称": "NVIDIA Corporation",
            "Percent": 1.2136333816049
        },
        {
            "代码": "ADBE",
            "名称": "Adobe Inc.",
            "Percent": 1.1941309272216856
        },
        {
            "代码": "CMCSA",
            "名称": "Comcast Corporation",
            "Percent": 0.79941191564995
        },
        {
            "代码": "GOOG",
            "名称": "Alphabet Inc.",
            "Percent": 0.7400558190852515
        },
        {
            "代码": "INTC",
            "名称": "Intel Corporation",
            "Percent": 0.6015839651583146
        },
        {
            "代码": "GOOGL",
            "名称": "Alphabet Inc.",
            "Percent": 0.5520000547071409
        },
        {
            "代码": "AMZN",
            "名称": "Amazon.com, Inc.",
            "Percent": 0.5242162086773894
        },
        {
            "代码": "INTU",
            "名称": "Intuit Inc.",
            "Percent": 0.5088458377683662
        },
        {
            "代码": "AAPL",
            "名称": "Apple Inc.",
            "Percent": 0.22601391151964495
        },
        {
            "代码": "COST",
            "名称": "Costco Wholesale Corporation",
            "Percent": 0.11141801444591302
        },
        {
            "代码": "META",
            "名称": "Meta Platforms, Inc.",
            "Percent": -0.10100311058668376
        },
        {
            "代码": "TMUS",
            "名称": "T-Mobile US, Inc.",
            "Percent": -0.7519459558439713
        },
        {
            "代码": "TSLA",
            "名称": "Tesla, Inc.",
            "Percent": -0.7896317464768929
        },
        {
            "代码": "QCOM",
            "名称": "QUALCOMM Incorporated",
            "Percent": -0.9735239670036996
        }
    ],
    "top_down_20": [
        {
            "代码": "QCOM",
            "名称": "QUALCOMM Incorporated",
            "Percent": -0.9735239670036996
        },
        {
            "代码": "TSLA",
            "名称": "Tesla, Inc.",
            "Percent": -0.7896317464768929
        },
        {
            "代码": "TMUS",
            "名称": "T-Mobile US, Inc.",
            "Percent": -0.7519459558439713
        },
        {
            "代码": "META",
            "名称": "Meta Platforms, Inc.",
            "Percent": -0.10100311058668376
        },
        {
            "代码": "COST",
            "名称": "Costco Wholesale Corporation",
            "Percent": 0.11141801444591302
        },
        {
            "代码": "AAPL",
            "名称": "Apple Inc.",
            "Percent": 0.22601391151964495
        },
        {
            "代码": "INTU",
            "名称": "Intuit Inc.",
            "Percent": 0.5088458377683662
        },
        {
            "代码": "AMZN",
            "名称": "Amazon.com, Inc.",
            "Percent": 0.5242162086773894
        },
        {
            "代码": "GOOGL",
            "名称": "Alphabet Inc.",
            "Percent": 0.5520000547071409
        },
        {
            "代码": "INTC",
            "名称": "Intel Corporation",
            "Percent": 0.6015839651583146
        },
        {
            "代码": "GOOG",
            "名称": "Alphabet Inc.",
            "Percent": 0.7400558190852515
        },
        {
            "代码": "CMCSA",
            "名称": "Comcast Corporation",
            "Percent": 0.79941191564995
        },
        {
            "代码": "ADBE",
            "名称": "Adobe Inc.",
            "Percent": 1.1941309272216856
        },
        {
            "代码": "NVDA",
            "名称": "NVIDIA Corporation",
            "Percent": 1.2136333816049
        },
        {
            "代码": "NVDA",
            "名称": "NVIDIA Corporation",
            "Percent": 1.2136333816049
        },
        {
            "代码": "MSFT",
            "名称": "Microsoft Corporation",
            "Percent": 1.315221802595292
        },
        {
            "代码": "CSCO",
            "名称": "Cisco Systems, Inc.",
            "Percent": 1.5506910790672277
        },
        {
            "代码": "NFLX",
            "名称": "Netflix, Inc.",
            "Percent": 1.8928215071652148
        },
        {
            "代码": "AVGO",
            "名称": "Broadcom Inc.",
            "Percent": 2.0423118546354315
        },
        {
            "代码": "PEP",
            "名称": "PepsiCo, Inc.",
            "Percent": 7.5212354759670985
        }
    ]
}