{
    "update_time_utc": "2025-07-10 15:27:18 UTC",
    "top_up_20": [
        {
            "代码": "AMD",
            "名称": "Advanced Micro Devices, Inc.",
            "Percent": 3.872619045781658
        },
        {
            "代码": "TSLA",
            "名称": "Tesla, Inc.",
            "Percent": 3.124575829599946
        },
        {
            "代码": "INTC",
            "名称": "Intel Corporation",
            "Percent": 1.6638198837998324
        },
        {
            "代码": "PEP",
            "名称": "PepsiCo, Inc.",
            "Percent": 1.3013087861376484
        },
        {
            "代码": "AAPL",
            "名称": "Apple Inc.",
            "Percent": 0.9803956285889031
        },
        {
            "代码": "QCOM",
            "名称": "QUALCOMM Incorporated",
            "Percent": 0.5083134782358063
        },
        {
            "代码": "CMCSA",
            "名称": "Comcast Corporation",
            "Percent": 0.4632254926308978
        },
        {
            "代码": "GOOG",
            "名称": "Alphabet Inc.",
            "Percent": -0.030962475197811996
        },
        {
            "代码": "GOOGL",
            "名称": "Alphabet Inc.",
            "Percent": -0.08889009455576896
        },
        {
            "代码": "NVDA",
            "名称": "NVIDIA Corporation",
            "Percent": -0.15963270986642564
        },
        {
            "代码": "NVDA",
            "名称": "NVIDIA Corporation",
            "Percent": -0.15963270986642564
        },
        {
            "代码": "AMZN",
            "名称": "Amazon.com, Inc.",
            "Percent": -0.4223902269146699
        },
        {
            "代码": "MSFT",
            "名称": "Microsoft Corporation",
            "Percent": -0.6534147248538944
        },
        {
            "代码": "ADBE",
            "名称": "Adobe Inc.",
            "Percent": -0.7325019640510813
        },
        {
            "代码": "CSCO",
            "名称": "Cisco Systems, Inc.",
            "Percent": -0.743466745497506
        },
        {
            "代码": "COST",
            "名称": "Costco Wholesale Corporation",
            "Percent": -0.7670272320489967
        },
        {
            "代码": "META",
            "名称": "Meta Platforms, Inc.",
            "Percent": -0.7751376243683505
        },
        {
            "代码": "AVGO",
            "名称": "Broadcom Inc.",
            "Percent": -1.2144656617938472
        },
        {
            "代码": "TMUS",
            "名称": "T-Mobile US, Inc.",
            "Percent": -2.0123985626484595
        },
        {
            "代码": "INTU",
            "名称": "Intuit Inc.",
            "Percent": -2.086825062457555
        }
    ],
    "top_down_20": [
        {
            "代码": "NFLX",
            "名称": "Netflix, Inc.",
            "Percent": -2.5239089257778633
        },
        {
            "代码": "INTU",
            "名称": "Intuit Inc.",
            "Percent": -2.086825062457555
        },
        {
            "代码": "TMUS",
            "名称": "T-Mobile US, Inc.",
            "Percent": -2.0123985626484595
        },
        {
            "代码": "AVGO",
            "名称": "Broadcom Inc.",
            "Percent": -1.2144656617938472
        },
        {
            "代码": "META",
            "名称": "Meta Platforms, Inc.",
            "Percent": -0.7751376243683505
        },
        {
            "代码": "COST",
            "名称": "Costco Wholesale Corporation",
            "Percent": -0.7670272320489967
        },
        {
            "代码": "CSCO",
            "名称": "Cisco Systems, Inc.",
            "Percent": -0.743466745497506
        },
        {
            "代码": "ADBE",
            "名称": "Adobe Inc.",
            "Percent": -0.7325019640510813
        },
        {
            "代码": "MSFT",
            "名称": "Microsoft Corporation",
            "Percent": -0.6534147248538944
        },
        {
            "代码": "AMZN",
            "名称": "Amazon.com, Inc.",
            "Percent": -0.4223902269146699
        },
        {
            "代码": "NVDA",
            "名称": "NVIDIA Corporation",
            "Percent": -0.15963270986642564
        },
        {
            "代码": "NVDA",
            "名称": "NVIDIA Corporation",
            "Percent": -0.15963270986642564
        },
        {
            "代码": "GOOGL",
            "名称": "Alphabet Inc.",
            "Percent": -0.08889009455576896
        },
        {
            "代码": "GOOG",
            "名称": "Alphabet Inc.",
            "Percent": -0.030962475197811996
        },
        {
            "代码": "CMCSA",
            "名称": "Comcast Corporation",
            "Percent": 0.4632254926308978
        },
        {
            "代码": "QCOM",
            "名称": "QUALCOMM Incorporated",
            "Percent": 0.5083134782358063
        },
        {
            "代码": "AAPL",
            "名称": "Apple Inc.",
            "Percent": 0.9803956285889031
        },
        {
            "代码": "PEP",
            "名称": "PepsiCo, Inc.",
            "Percent": 1.3013087861376484
        },
        {
            "代码": "INTC",
            "名称": "Intel Corporation",
            "Percent": 1.6638198837998324
        },
        {
            "代码": "TSLA",
            "名称": "Tesla, Inc.",
            "Percent": 3.124575829599946
        }
    ]
}