{
    "update_time_utc": "2025-07-11 19:52:50 UTC",
    "top_up_20": [
        {
            "代码": "AMD",
            "名称": "Advanced Micro Devices, Inc.",
            "Percent": 1.7966122864155925
        },
        {
            "代码": "GOOG",
            "名称": "Alphabet Inc.",
            "Percent": 1.5109702327234342
        },
        {
            "代码": "GOOGL",
            "名称": "Alphabet Inc.",
            "Percent": 1.4919543002605384
        },
        {
            "代码": "AMZN",
            "名称": "Amazon.com, Inc.",
            "Percent": 1.4757486098992922
        },
        {
            "代码": "NVDA",
            "名称": "NVIDIA Corporation",
            "Percent": 0.630705889594808
        },
        {
            "代码": "NVDA",
            "名称": "NVIDIA Corporation",
            "Percent": 0.630705889594808
        },
        {
            "代码": "MSFT",
            "名称": "Microsoft Corporation",
            "Percent": 0.43769976041985587
        },
        {
            "代码": "COST",
            "名称": "Costco Wholesale Corporation",
            "Percent": -0.04225786735861277
        },
        {
            "代码": "INTU",
            "名称": "Intuit Inc.",
            "Percent": -0.09627379526365897
        },
        {
            "代码": "TMUS",
            "名称": "T-Mobile US, Inc.",
            "Percent": -0.1402551277625164
        },
        {
            "代码": "AVGO",
            "名称": "Broadcom Inc.",
            "Percent": -0.2608510548233787
        },
        {
            "代码": "NFLX",
            "名称": "Netflix, Inc.",
            "Percent": -0.427395937054318
        },
        {
            "代码": "AAPL",
            "名称": "Apple Inc.",
            "Percent": -0.5696561805026858
        },
        {
            "代码": "PEP",
            "名称": "PepsiCo, Inc.",
            "Percent": -0.6036124801373919
        },
        {
            "代码": "QCOM",
            "名称": "QUALCOMM Incorporated",
            "Percent": -0.7354316398753056
        },
        {
            "代码": "CSCO",
            "名称": "Cisco Systems, Inc.",
            "Percent": -1.1416574137884548
        },
        {
            "代码": "CMCSA",
            "名称": "Comcast Corporation",
            "Percent": -1.1434184083384848
        },
        {
            "代码": "META",
            "名称": "Meta Platforms, Inc.",
            "Percent": -1.4445031934268282
        },
        {
            "代码": "ADBE",
            "名称": "Adobe Inc.",
            "Percent": -2.204992220042728
        }
    ],
    "top_down_20": [
        {
            "代码": "ADBE",
            "名称": "Adobe Inc.",
            "Percent": -2.204992220042728
        },
        {
            "代码": "META",
            "名称": "Meta Platforms, Inc.",
            "Percent": -1.4445031934268282
        },
        {
            "代码": "CMCSA",
            "名称": "Comcast Corporation",
            "Percent": -1.1434184083384848
        },
        {
            "代码": "CSCO",
            "名称": "Cisco Systems, Inc.",
            "Percent": -1.1416574137884548
        },
        {
            "代码": "QCOM",
            "名称": "QUALCOMM Incorporated",
            "Percent": -0.7354316398753056
        },
        {
            "代码": "PEP",
            "名称": "PepsiCo, Inc.",
            "Percent": -0.6036124801373919
        },
        {
            "代码": "AAPL",
            "名称": "Apple Inc.",
            "Percent": -0.5696561805026858
        },
        {
            "代码": "NFLX",
            "名称": "Netflix, Inc.",
            "Percent": -0.427395937054318
        },
        {
            "代码": "AVGO",
            "名称": "Broadcom Inc.",
            "Percent": -0.2608510548233787
        },
        {
            "代码": "TMUS",
            "名称": "T-Mobile US, Inc.",
            "Percent": -0.1402551277625164
        },
        {
            "代码": "INTU",
            "名称": "Intuit Inc.",
            "Percent": -0.09627379526365897
        },
        {
            "代码": "COST",
            "名称": "Costco Wholesale Corporation",
            "Percent": -0.04225786735861277
        },
        {
            "代码": "MSFT",
            "名称": "Microsoft Corporation",
            "Percent": 0.43769976041985587
        },
        {
            "代码": "NVDA",
            "名称": "NVIDIA Corporation",
            "Percent": 0.630705889594808
        },
        {
            "代码": "NVDA",
            "名称": "NVIDIA Corporation",
            "Percent": 0.630705889594808
        },
        {
            "代码": "AMZN",
            "名称": "Amazon.com, Inc.",
            "Percent": 1.4757486098992922
        },
        {
            "代码": "GOOGL",
            "名称": "Alphabet Inc.",
            "Percent": 1.4919543002605384
        },
        {
            "代码": "GOOG",
            "名称": "Alphabet Inc.",
            "Percent": 1.5109702327234342
        },
        {
            "代码": "AMD",
            "名称": "Advanced Micro Devices, Inc.",
            "Percent": 1.7966122864155925
        }
    ]
}