{
    "update_time_utc": "2025-07-10 20:46:03 UTC",
    "top_up_20": [
        {
            "代码": "TSLA",
            "名称": "Tesla, Inc.",
            "Percent": 4.728264838279942
        },
        {
            "代码": "AMD",
            "名称": "Advanced Micro Devices, Inc.",
            "Percent": 4.154323999612825
        },
        {
            "代码": "INTC",
            "名称": "Intel Corporation",
            "Percent": 1.6211567922725691
        },
        {
            "代码": "PEP",
            "名称": "PepsiCo, Inc.",
            "Percent": 1.189772571644998
        },
        {
            "代码": "NVDA",
            "名称": "NVIDIA Corporation",
            "Percent": 0.7490184087241899
        },
        {
            "代码": "NVDA",
            "名称": "NVIDIA Corporation",
            "Percent": 0.7490184087241899
        },
        {
            "代码": "AAPL",
            "名称": "Apple Inc.",
            "Percent": 0.6014986625614256
        },
        {
            "代码": "GOOG",
            "名称": "Alphabet Inc.",
            "Percent": 0.585384028309923
        },
        {
            "代码": "GOOGL",
            "名称": "Alphabet Inc.",
            "Percent": 0.566187310409843
        },
        {
            "代码": "AMZN",
            "名称": "Amazon.com, Inc.",
            "Percent": -0.1258195325533528
        },
        {
            "代码": "QCOM",
            "名称": "QUALCOMM Incorporated",
            "Percent": -0.16316897123687252
        },
        {
            "代码": "MSFT",
            "名称": "Microsoft Corporation",
            "Percent": -0.4031694981082508
        },
        {
            "代码": "ADBE",
            "名称": "Adobe Inc.",
            "Percent": -0.5222594090551991
        },
        {
            "代码": "CMCSA",
            "名称": "Comcast Corporation",
            "Percent": -0.5614844720290688
        },
        {
            "代码": "CSCO",
            "名称": "Cisco Systems, Inc.",
            "Percent": -0.7362415642429304
        },
        {
            "代码": "META",
            "名称": "Meta Platforms, Inc.",
            "Percent": -0.7560303011827216
        },
        {
            "代码": "AVGO",
            "名称": "Broadcom Inc.",
            "Percent": -0.8996041939213683
        },
        {
            "代码": "COST",
            "名称": "Costco Wholesale Corporation",
            "Percent": -1.2137424899302778
        },
        {
            "代码": "TMUS",
            "名称": "T-Mobile US, Inc.",
            "Percent": -1.7907122835125207
        },
        {
            "代码": "INTU",
            "名称": "Intuit Inc.",
            "Percent": -2.8183840336433694
        }
    ],
    "top_down_20": [
        {
            "代码": "NFLX",
            "名称": "Netflix, Inc.",
            "Percent": -2.925611095371338
        },
        {
            "代码": "INTU",
            "名称": "Intuit Inc.",
            "Percent": -2.8183840336433694
        },
        {
            "代码": "TMUS",
            "名称": "T-Mobile US, Inc.",
            "Percent": -1.7907122835125207
        },
        {
            "代码": "COST",
            "名称": "Costco Wholesale Corporation",
            "Percent": -1.2137424899302778
        },
        {
            "代码": "AVGO",
            "名称": "Broadcom Inc.",
            "Percent": -0.8996041939213683
        },
        {
            "代码": "META",
            "名称": "Meta Platforms, Inc.",
            "Percent": -0.7560303011827216
        },
        {
            "代码": "CSCO",
            "名称": "Cisco Systems, Inc.",
            "Percent": -0.7362415642429304
        },
        {
            "代码": "CMCSA",
            "名称": "Comcast Corporation",
            "Percent": -0.5614844720290688
        },
        {
            "代码": "ADBE",
            "名称": "Adobe Inc.",
            "Percent": -0.5222594090551991
        },
        {
            "代码": "MSFT",
            "名称": "Microsoft Corporation",
            "Percent": -0.4031694981082508
        },
        {
            "代码": "QCOM",
            "名称": "QUALCOMM Incorporated",
            "Percent": -0.16316897123687252
        },
        {
            "代码": "AMZN",
            "名称": "Amazon.com, Inc.",
            "Percent": -0.1258195325533528
        },
        {
            "代码": "GOOGL",
            "名称": "Alphabet Inc.",
            "Percent": 0.566187310409843
        },
        {
            "代码": "GOOG",
            "名称": "Alphabet Inc.",
            "Percent": 0.585384028309923
        },
        {
            "代码": "AAPL",
            "名称": "Apple Inc.",
            "Percent": 0.6014986625614256
        },
        {
            "代码": "NVDA",
            "名称": "NVIDIA Corporation",
            "Percent": 0.7490184087241899
        },
        {
            "代码": "NVDA",
            "名称": "NVIDIA Corporation",
            "Percent": 0.7490184087241899
        },
        {
            "代码": "PEP",
            "名称": "PepsiCo, Inc.",
            "Percent": 1.189772571644998
        },
        {
            "代码": "INTC",
            "名称": "Intel Corporation",
            "Percent": 1.6211567922725691
        },
        {
            "代码": "AMD",
            "名称": "Advanced Micro Devices, Inc.",
            "Percent": 4.154323999612825
        }
    ]
}